api_service/__init__.py
api_service/encryption.py
api_service/query.py
api_service-0.0.5.dist-info/METADATA
api_service-0.0.5.dist-info/WHEEL
api_service-0.0.5.dist-info/top_level.txt
api_service-0.0.5.dist-info/RECORD
