Metadata-Version: 2.1
Name: api_service
Version: 0.0.5
Summary: This library will create and validate JWT tokens
Author: Alfonso Falcone
Keywords: fastapi,bcrypt,jwt,pydantic
Requires-Dist: fastapi>=0.103.1
Requires-Dist: python-decouple>=3.8
Requires-Dist: bcrypt>=4.0.1
Requires-Dist: pydantic[email]>=2.4.2
